fast_ivf/__init__.py
fast_ivf/core.py
fast_ivf/index.py
fast_ivf/kmeans.py
fast_ivf/tf_compressor.py
fast_ivf/version.py
fast_ivf-1.0.1.dist-info/LICENSE
fast_ivf-1.0.1.dist-info/METADATA
fast_ivf-1.0.1.dist-info/WHEEL
fast_ivf-1.0.1.dist-info/top_level.txt
fast_ivf-1.0.1.dist-info/RECORD
