Metadata-Version: 2.1
Name: fast-ivf
Version: 1.0.1
Summary: Efficient implementation of IVF + IVFPQ Index with numpy and numba
Home-page: https://github.com/kmkolasinski/fast-ivf
Author: Krzysztof Kolasinski
Author-email: kmkolasinski@gmail.com
Classifier: Programming Language :: Python :: 3
Classifier: Operating System :: OS Independent
License-File: LICENSE
Requires-Dist: numba >=0.58.0
Requires-Dist: numpy >=1.24.3
Requires-Dist: tqdm
